{
    "nodes": [
        0,
        1,
        2,
        3,
        4,
        5,
        6,
        7,
        8,
        9,
        10,
        11
    ],
    "parents": {
        "0": [
            1,
            5,
            6,
            7
        ],
        "1": [
            4,
            6,
            8,
            9,
            10,
            11
        ],
        "2": [
            5,
            7
        ],
        "3": [
            4,
            5,
            7,
            8,
            9
        ],
        "4": [
            5,
            8,
            11
        ],
        "5": [
            7,
            9,
            11
        ],
        "6": [],
        "7": [
            9
        ],
        "8": [],
        "9": [
            10
        ],
        "10": [
            11
        ],
        "11": []
    },
    "edges": {
        "1->0": {
            "type": "linear",
            "weight": -0.9070186539043466
        },
        "5->0": {
            "type": "linear",
            "weight": -0.13667036680750266
        },
        "6->0": {
            "type": "linear",
            "weight": 0.9008113006829968
        },
        "7->0": {
            "type": "linear",
            "weight": -0.9481064862219588
        },
        "4->1": {
            "type": "linear",
            "weight": -0.6388306260885881
        },
        "6->1": {
            "type": "linear",
            "weight": -1.2746922905569602
        },
        "8->1": {
            "type": "linear",
            "weight": 1.081229485003036
        },
        "9->1": {
            "type": "linear",
            "weight": -0.8890679497006859
        },
        "10->1": {
            "type": "linear",
            "weight": 1.2596356997252145
        },
        "11->1": {
            "type": "linear",
            "weight": 1.5589721770048102
        },
        "5->2": {
            "type": "linear",
            "weight": 1.1617434259162192
        },
        "7->2": {
            "type": "linear",
            "weight": -1.7094135476137953
        },
        "4->3": {
            "type": "linear",
            "weight": 1.6177572069807509
        },
        "5->3": {
            "type": "linear",
            "weight": 0.26496076558539183
        },
        "7->3": {
            "type": "linear",
            "weight": -0.17773476602260896
        },
        "8->3": {
            "type": "linear",
            "weight": -0.56982686499975
        },
        "9->3": {
            "type": "linear",
            "weight": 1.825282636172172
        },
        "5->4": {
            "type": "linear",
            "weight": 0.19297634451504342
        },
        "8->4": {
            "type": "linear",
            "weight": -0.31286312513113135
        },
        "11->4": {
            "type": "linear",
            "weight": -1.5958175613771783
        },
        "7->5": {
            "type": "linear",
            "weight": -1.6975677319224407
        },
        "9->5": {
            "type": "linear",
            "weight": 0.13792791075467203
        },
        "11->5": {
            "type": "linear",
            "weight": 1.6998037697078234
        },
        "9->7": {
            "type": "linear",
            "weight": -1.0103543169477014
        },
        "10->9": {
            "type": "linear",
            "weight": 0.8208485037148638
        },
        "11->10": {
            "type": "linear",
            "weight": 1.2041047037323294
        }
    },
    "mechanisms": {
        "0": "linear",
        "0_weights": [
            -0.9070186539043466,
            -0.13667036680750266,
            0.9008113006829968,
            -0.9481064862219588
        ],
        "1": "linear",
        "1_weights": [
            -0.6388306260885881,
            -1.2746922905569602,
            1.081229485003036,
            -0.8890679497006859,
            1.2596356997252145,
            1.5589721770048102
        ],
        "2": "linear",
        "2_weights": [
            1.1617434259162192,
            -1.7094135476137953
        ],
        "3": "linear",
        "3_weights": [
            1.6177572069807509,
            0.26496076558539183,
            -0.17773476602260896,
            -0.56982686499975,
            1.825282636172172
        ],
        "4": "linear",
        "4_weights": [
            0.19297634451504342,
            -0.31286312513113135,
            -1.5958175613771783
        ],
        "5": "linear",
        "5_weights": [
            -1.6975677319224407,
            0.13792791075467203,
            1.6998037697078234
        ],
        "6": "linear",
        "7": "linear",
        "7_weights": [
            -1.0103543169477014
        ],
        "8": "linear",
        "9": "linear",
        "9_weights": [
            0.8208485037148638
        ],
        "10": "linear",
        "10_weights": [
            1.2041047037323294
        ],
        "11": "linear"
    },
    "intervened_nodes": [
        11,
        9
    ],
    "adjacency_matrix_shape": [
        12,
        12
    ]
}